ntnx_multidomain_py_client/__init__.py
ntnx_multidomain_py_client/api_client.py
ntnx_multidomain_py_client/api_response.py
ntnx_multidomain_py_client/configuration.py
ntnx_multidomain_py_client/custom_retry.py
ntnx_multidomain_py_client/rest.py
ntnx_multidomain_py_client/api/__init__.py
ntnx_multidomain_py_client/api/external_repositories_api.py
ntnx_multidomain_py_client/models/__init__.py
ntnx_multidomain_py_client/models/OneOfcommon/__init__.py
ntnx_multidomain_py_client/models/OneOfcommon/v1/__init__.py
ntnx_multidomain_py_client/models/OneOfcommon/v1/config/KVPairvalue.py
ntnx_multidomain_py_client/models/OneOfcommon/v1/config/__init__.py
ntnx_multidomain_py_client/models/OneOfmultidomain/__init__.py
ntnx_multidomain_py_client/models/OneOfmultidomain/v4/__init__.py
ntnx_multidomain_py_client/models/OneOfmultidomain/v4/config/CreateExternalRepositoryApiResponsedata.py
ntnx_multidomain_py_client/models/OneOfmultidomain/v4/config/DeleteExternalRepositoryApiResponsedata.py
ntnx_multidomain_py_client/models/OneOfmultidomain/v4/config/ExternalRepositorylocation.py
ntnx_multidomain_py_client/models/OneOfmultidomain/v4/config/GetExternalRepositoryApiResponsedata.py
ntnx_multidomain_py_client/models/OneOfmultidomain/v4/config/ListExternalRepositoriesApiResponsedata.py
ntnx_multidomain_py_client/models/OneOfmultidomain/v4/config/UpdateExternalRepositoryApiResponsedata.py
ntnx_multidomain_py_client/models/OneOfmultidomain/v4/config/__init__.py
ntnx_multidomain_py_client/models/OneOfmultidomain/v4/error/ErrorResponseerror.py
ntnx_multidomain_py_client/models/OneOfmultidomain/v4/error/__init__.py
ntnx_multidomain_py_client/models/common/__init__.py
ntnx_multidomain_py_client/models/common/v1/__init__.py
ntnx_multidomain_py_client/models/common/v1/config/FQDN.py
ntnx_multidomain_py_client/models/common/v1/config/Flag.py
ntnx_multidomain_py_client/models/common/v1/config/IPAddressOrFQDN.py
ntnx_multidomain_py_client/models/common/v1/config/IPv4Address.py
ntnx_multidomain_py_client-4.2.1.dist-info/LICENSE.txt
ntnx_multidomain_py_client-4.2.1.dist-info/METADATA
ntnx_multidomain_py_client-4.2.1.dist-info/WHEEL
ntnx_multidomain_py_client-4.2.1.dist-info/top_level.txt
ntnx_multidomain_py_client-4.2.1.dist-info/RECORD
